{
  "updated_at": "2026-04-29T02:18:43.006839",
  "assets": {
    "XAUUSD": {
      "error": true,
      "name": "黄金",
      "updated": "2026-04-29T02:18:45.382657"
    },
    "GLD.US": {
      "error": true,
      "name": "黄金ETF",
      "updated": "2026-04-29T02:18:45.383151"
    },
    "XAGUSD": {
      "error": true,
      "name": "白银",
      "updated": "2026-04-29T02:18:47.751108"
    },
    "SLV.US": {
      "error": true,
      "name": "白银ETF",
      "updated": "2026-04-29T02:18:47.751322"
    },
    "HG=F": {
      "price": 6.002999782562256,
      "change_pct": -0.24925794298729678,
      "prev_close": 6.01800012588501,
      "name": "铜",
      "updated": "2026-04-29T02:18:48.315585",
      "unit": "USD/吨",
      "icon": "🔶",
      "category": "metals"
    },
    "NICK.L": {
      "price": NaN,
      "change_pct": NaN,
      "prev_close": 16.780000686645508,
      "name": "镍",
      "updated": "2026-04-29T02:18:48.555536",
      "unit": "USD (ETC)",
      "icon": "⚙️",
      "category": "metals"
    },
    "CL=F": {
      "price": 99.75,
      "change_pct": 3.507312604635002,
      "prev_close": 96.37000274658203,
      "name": "WTI原油",
      "updated": "2026-04-29T02:18:48.695765",
      "unit": "USD/桶",
      "icon": "🛢️",
      "category": "commodities"
    },
    "BTC-USD.CC": {
      "error": true,
      "name": "BTC",
      "updated": "2026-04-29T02:18:48.696151"
    },
    "ETH-USD.CC": {
      "error": true,
      "name": "ETH",
      "updated": "2026-04-29T02:18:48.696239"
    },
    "USDCNY.FOREX": {
      "error": true,
      "name": "USD/CNY",
      "updated": "2026-04-29T02:18:48.696343"
    },
    "USDJPY.FOREX": {
      "error": true,
      "name": "USD/JPY",
      "updated": "2026-04-29T02:18:48.696419"
    },
    "EURUSD.FOREX": {
      "error": true,
      "name": "USD/EUR",
      "updated": "2026-04-29T02:18:48.696488"
    }
  },
  "meta": {
    "total_assets": 12,
    "successful_fetches": 3,
    "failed_fetches": 9
  }
}