{
  "updated_at": "2026-06-05T02:47:14.497197",
  "assets": {
    "XAUUSD": {
      "error": true,
      "name": "黄金",
      "updated": "2026-06-05T02:47:16.951705"
    },
    "GLD.US": {
      "error": true,
      "name": "黄金ETF",
      "updated": "2026-06-05T02:47:16.952140"
    },
    "XAGUSD": {
      "error": true,
      "name": "白银",
      "updated": "2026-06-05T02:47:19.072993"
    },
    "SLV.US": {
      "error": true,
      "name": "白银ETF",
      "updated": "2026-06-05T02:47:19.073182"
    },
    "HG=F": {
      "price": 6.451499938964844,
      "change_pct": -0.4551767917371573,
      "prev_close": 6.480999946594238,
      "name": "铜",
      "updated": "2026-06-05T02:47:19.377807",
      "unit": "USD/吨",
      "icon": "🔶",
      "category": "metals"
    },
    "NICK.L": {
      "price": NaN,
      "change_pct": NaN,
      "prev_close": 16.475000381469727,
      "name": "镍",
      "updated": "2026-06-05T02:47:19.454383",
      "unit": "USD (ETC)",
      "icon": "⚙️",
      "category": "metals"
    },
    "CL=F": {
      "price": 93.41000366210938,
      "change_pct": -2.7181764967761,
      "prev_close": 96.0199966430664,
      "name": "WTI原油",
      "updated": "2026-06-05T02:47:19.523269",
      "unit": "USD/桶",
      "icon": "🛢️",
      "category": "commodities"
    },
    "BTC-USD.CC": {
      "error": true,
      "name": "BTC",
      "updated": "2026-06-05T02:47:19.523606"
    },
    "ETH-USD.CC": {
      "error": true,
      "name": "ETH",
      "updated": "2026-06-05T02:47:19.523695"
    },
    "USDCNY.FOREX": {
      "error": true,
      "name": "USD/CNY",
      "updated": "2026-06-05T02:47:19.523761"
    },
    "USDJPY.FOREX": {
      "error": true,
      "name": "USD/JPY",
      "updated": "2026-06-05T02:47:19.523821"
    },
    "EURUSD.FOREX": {
      "error": true,
      "name": "USD/EUR",
      "updated": "2026-06-05T02:47:19.523873"
    },
    "US10Y.INDX": {
      "error": true,
      "name": "美国10年期国债收益率",
      "updated": "2026-06-05T02:47:19.523934"
    },
    "US30Y.INDX": {
      "error": true,
      "name": "美国30年期国债收益率",
      "updated": "2026-06-05T02:47:19.523991"
    },
    "HIBOR1M": {
      "price": 2.60923,
      "change_pct": -1.5915939700463444,
      "prev_close": 2.65143,
      "name": "香港1个月HIBOR",
      "updated": "2026-06-05T02:47:20.784156",
      "unit": "%",
      "icon": "🇭🇰",
      "category": "rates"
    }
  },
  "meta": {
    "total_assets": 15,
    "successful_fetches": 4,
    "failed_fetches": 11
  }
}