{
  "updated_at": "2026-04-27T06:36:43.760657",
  "assets": {
    "XAUUSD": {
      "error": true,
      "name": "黄金",
      "updated": "2026-04-27T06:36:46.311675"
    },
    "GLD.US": {
      "error": true,
      "name": "黄金ETF",
      "updated": "2026-04-27T06:36:46.312063"
    },
    "XAGUSD": {
      "error": true,
      "name": "白银",
      "updated": "2026-04-27T06:36:48.671620"
    },
    "SLV.US": {
      "error": true,
      "name": "白银ETF",
      "updated": "2026-04-27T06:36:48.671945"
    },
    "HG=F": {
      "price": 6.039000034332275,
      "change_pct": 0.2573266166331346,
      "prev_close": 6.023499965667725,
      "name": "铜",
      "updated": "2026-04-27T06:36:48.962020",
      "unit": "USD/吨",
      "icon": "🔶",
      "category": "metals"
    },
    "NICK.L": {
      "price": 16.684999465942383,
      "change_pct": 1.8620288205283824,
      "prev_close": 16.3799991607666,
      "name": "镍",
      "updated": "2026-04-27T06:36:49.048259",
      "unit": "USD (ETC)",
      "icon": "⚙️",
      "category": "metals"
    },
    "CL=F": {
      "price": 96.20999908447266,
      "change_pct": 1.9173702641281796,
      "prev_close": 94.4000015258789,
      "name": "WTI原油",
      "updated": "2026-04-27T06:36:49.126654",
      "unit": "USD/桶",
      "icon": "🛢️",
      "category": "commodities"
    },
    "BTC-USD.CC": {
      "error": true,
      "name": "BTC",
      "updated": "2026-04-27T06:36:49.126978"
    },
    "ETH-USD.CC": {
      "error": true,
      "name": "ETH",
      "updated": "2026-04-27T06:36:49.127073"
    },
    "USDCNY.FOREX": {
      "error": true,
      "name": "USD/CNY",
      "updated": "2026-04-27T06:36:49.127159"
    },
    "USDJPY.FOREX": {
      "error": true,
      "name": "USD/JPY",
      "updated": "2026-04-27T06:36:49.127245"
    },
    "EURUSD.FOREX": {
      "error": true,
      "name": "USD/EUR",
      "updated": "2026-04-27T06:36:49.127366"
    }
  },
  "meta": {
    "total_assets": 12,
    "successful_fetches": 3,
    "failed_fetches": 9
  }
}