{
  "updated_at": "2026-04-10T19:57:47.867738",
  "assets": {
    "XAUUSD": {
      "error": true,
      "name": "黄金",
      "updated": "2026-04-10T19:57:50.266015"
    },
    "GLD.US": {
      "error": true,
      "name": "黄金ETF",
      "updated": "2026-04-10T19:57:50.266637"
    },
    "XAGUSD": {
      "error": true,
      "name": "白银",
      "updated": "2026-04-10T19:57:52.501112"
    },
    "SLV.US": {
      "error": true,
      "name": "白银ETF",
      "updated": "2026-04-10T19:57:52.501408"
    },
    "HG=F": {
      "price": 5.871500015258789,
      "change_pct": 2.148571106224019,
      "prev_close": 5.748000144958496,
      "name": "铜",
      "updated": "2026-04-10T19:57:52.739418",
      "unit": "USD/吨",
      "icon": "🔶",
      "category": "metals"
    },
    "NICK.L": {
      "price": 15.0649995803833,
      "change_pct": 0.5003322909293293,
      "prev_close": 14.989999771118164,
      "name": "镍",
      "updated": "2026-04-10T19:57:52.815444",
      "unit": "USD (ETC)",
      "icon": "⚙️",
      "category": "metals"
    },
    "CL=F": {
      "price": 96.18000030517578,
      "change_pct": -1.7267828690903666,
      "prev_close": 97.87000274658203,
      "name": "WTI原油",
      "updated": "2026-04-10T19:57:52.885491",
      "unit": "USD/桶",
      "icon": "🛢️",
      "category": "commodities"
    },
    "BTC-USD.CC": {
      "error": true,
      "name": "BTC",
      "updated": "2026-04-10T19:57:52.885904"
    },
    "ETH-USD.CC": {
      "error": true,
      "name": "ETH",
      "updated": "2026-04-10T19:57:52.886024"
    },
    "USDCNY.FOREX": {
      "error": true,
      "name": "USD/CNY",
      "updated": "2026-04-10T19:57:52.886132"
    },
    "USDJPY.FOREX": {
      "error": true,
      "name": "USD/JPY",
      "updated": "2026-04-10T19:57:52.886236"
    },
    "EURUSD.FOREX": {
      "error": true,
      "name": "USD/EUR",
      "updated": "2026-04-10T19:57:52.886338"
    }
  },
  "meta": {
    "total_assets": 12,
    "successful_fetches": 3,
    "failed_fetches": 9
  }
}