{
  "updated_at": "2026-03-19T22:24:37.688062",
  "assets": {
    "XAUUSD": {
      "error": true,
      "name": "黄金",
      "updated": "2026-03-19T22:24:40.018315"
    },
    "GLD.US": {
      "error": true,
      "name": "黄金ETF",
      "updated": "2026-03-19T22:24:40.018704"
    },
    "XAGUSD": {
      "error": true,
      "name": "白银",
      "updated": "2026-03-19T22:24:42.165224"
    },
    "SLV.US": {
      "error": true,
      "name": "白银ETF",
      "updated": "2026-03-19T22:24:42.165630"
    },
    "HG=F": {
      "price": 5.5279998779296875,
      "change_pct": -0.4681314971639607,
      "prev_close": 5.553999900817871,
      "name": "铜",
      "updated": "2026-03-19T22:24:42.368677",
      "unit": "USD/吨",
      "icon": "🔶",
      "category": "metals"
    },
    "NICK.L": {
      "price": 14.904999732971191,
      "change_pct": -0.9634581789104402,
      "prev_close": 15.050000190734863,
      "name": "镍",
      "updated": "2026-03-19T22:24:42.445302",
      "unit": "USD (ETC)",
      "icon": "⚙️",
      "category": "metals"
    },
    "CL=F": {
      "price": 94.61000061035156,
      "change_pct": -1.7753312810325346,
      "prev_close": 96.31999969482422,
      "name": "WTI原油",
      "updated": "2026-03-19T22:24:42.528757",
      "unit": "USD/桶",
      "icon": "🛢️",
      "category": "commodities"
    },
    "BTC-USD.CC": {
      "error": true,
      "name": "BTC",
      "updated": "2026-03-19T22:24:42.529055"
    },
    "ETH-USD.CC": {
      "error": true,
      "name": "ETH",
      "updated": "2026-03-19T22:24:42.529156"
    },
    "USDCNY.FOREX": {
      "error": true,
      "name": "USD/CNY",
      "updated": "2026-03-19T22:24:42.529255"
    },
    "USDJPY.FOREX": {
      "error": true,
      "name": "USD/JPY",
      "updated": "2026-03-19T22:24:42.529371"
    },
    "EURUSD.FOREX": {
      "error": true,
      "name": "USD/EUR",
      "updated": "2026-03-19T22:24:42.529462"
    }
  },
  "meta": {
    "total_assets": 12,
    "successful_fetches": 3,
    "failed_fetches": 9
  }
}