{
  "updated_at": "2026-03-20T19:15:51.006739",
  "assets": {
    "XAUUSD": {
      "error": true,
      "name": "黄金",
      "updated": "2026-03-20T19:15:53.510343"
    },
    "GLD.US": {
      "error": true,
      "name": "黄金ETF",
      "updated": "2026-03-20T19:15:53.510768"
    },
    "XAGUSD": {
      "error": true,
      "name": "白银",
      "updated": "2026-03-20T19:15:55.866355"
    },
    "SLV.US": {
      "error": true,
      "name": "白银ETF",
      "updated": "2026-03-20T19:15:55.866726"
    },
    "HG=F": {
      "price": 5.331999778747559,
      "change_pct": -1.8590154124685236,
      "prev_close": 5.433000087738037,
      "name": "铜",
      "updated": "2026-03-20T19:15:56.505721",
      "unit": "USD/吨",
      "icon": "🔶",
      "category": "metals"
    },
    "NICK.L": {
      "price": 14.899999618530273,
      "change_pct": -0.03354655840655447,
      "prev_close": 14.904999732971191,
      "name": "镍",
      "updated": "2026-03-20T19:15:56.711128",
      "unit": "USD (ETC)",
      "icon": "⚙️",
      "category": "metals"
    },
    "CL=F": {
      "price": 98.58999633789062,
      "change_pct": 2.5483638067361825,
      "prev_close": 96.13999938964844,
      "name": "WTI原油",
      "updated": "2026-03-20T19:15:56.953281",
      "unit": "USD/桶",
      "icon": "🛢️",
      "category": "commodities"
    },
    "BTC-USD.CC": {
      "error": true,
      "name": "BTC",
      "updated": "2026-03-20T19:15:56.953626"
    },
    "ETH-USD.CC": {
      "error": true,
      "name": "ETH",
      "updated": "2026-03-20T19:15:56.953696"
    },
    "USDCNY.FOREX": {
      "error": true,
      "name": "USD/CNY",
      "updated": "2026-03-20T19:15:56.953757"
    },
    "USDJPY.FOREX": {
      "error": true,
      "name": "USD/JPY",
      "updated": "2026-03-20T19:15:56.953809"
    },
    "EURUSD.FOREX": {
      "error": true,
      "name": "USD/EUR",
      "updated": "2026-03-20T19:15:56.953871"
    }
  },
  "meta": {
    "total_assets": 12,
    "successful_fetches": 3,
    "failed_fetches": 9
  }
}