{
  "updated_at": "2026-07-06T23:50:34.826740",
  "assets": {
    "XAUUSD": {
      "error": true,
      "name": "黄金",
      "updated": "2026-07-06T23:50:37.132099"
    },
    "GLD.US": {
      "error": true,
      "name": "黄金ETF",
      "updated": "2026-07-06T23:50:37.132531"
    },
    "XAGUSD": {
      "error": true,
      "name": "白银",
      "updated": "2026-07-06T23:50:39.341616"
    },
    "SLV.US": {
      "error": true,
      "name": "白银ETF",
      "updated": "2026-07-06T23:50:39.341819"
    },
    "HG=F": {
      "price": 6.248000144958496,
      "change_pct": 2.183336301949086,
      "prev_close": 6.114500045776367,
      "name": "铜",
      "updated": "2026-07-06T23:50:39.565799",
      "unit": "USD/吨",
      "icon": "🔶",
      "category": "metals"
    },
    "NICK.L": {
      "price": 14.239999771118164,
      "change_pct": 0.5294727106750055,
      "prev_close": 14.164999961853027,
      "name": "镍",
      "updated": "2026-07-06T23:50:39.651155",
      "unit": "USD (ETC)",
      "icon": "⚙️",
      "category": "metals"
    },
    "CL=F": {
      "price": 68.80000305175781,
      "change_pct": 0.16014064120232768,
      "prev_close": 68.69000244140625,
      "name": "WTI原油",
      "updated": "2026-07-06T23:50:39.724587",
      "unit": "USD/桶",
      "icon": "🛢️",
      "category": "commodities"
    },
    "BZ=F": {
      "price": 72.2300033569336,
      "change_pct": 0.5988861934529597,
      "prev_close": 71.80000305175781,
      "name": "布伦特原油",
      "updated": "2026-07-06T23:50:39.832562",
      "unit": "USD/桶",
      "icon": "🛢️",
      "category": "commodities"
    },
    "BTC-USD.CC": {
      "error": true,
      "name": "BTC",
      "updated": "2026-07-06T23:50:39.832912"
    },
    "ETH-USD.CC": {
      "error": true,
      "name": "ETH",
      "updated": "2026-07-06T23:50:39.833019"
    },
    "USDCNY.FOREX": {
      "error": true,
      "name": "USD/CNY",
      "updated": "2026-07-06T23:50:39.833117"
    },
    "USDJPY.FOREX": {
      "error": true,
      "name": "USD/JPY",
      "updated": "2026-07-06T23:50:39.833212"
    },
    "EURUSD.FOREX": {
      "error": true,
      "name": "USD/EUR",
      "updated": "2026-07-06T23:50:39.833304"
    },
    "US10Y.INDX": {
      "error": true,
      "name": "美国10年期国债收益率",
      "updated": "2026-07-06T23:50:39.833427"
    },
    "US30Y.INDX": {
      "error": true,
      "name": "美国30年期国债收益率",
      "updated": "2026-07-06T23:50:39.833534"
    },
    "HIBOR1M": {
      "price": 2.93976,
      "change_pct": -0.29270211878346125,
      "prev_close": 2.94839,
      "name": "香港1个月HIBOR",
      "updated": "2026-07-06T23:50:41.039334",
      "unit": "%",
      "icon": "🇭🇰",
      "category": "rates"
    }
  },
  "meta": {
    "total_assets": 16,
    "successful_fetches": 5,
    "failed_fetches": 11
  }
}