{
  "updated_at": "2026-05-19T00:08:26.607106",
  "assets": {
    "XAUUSD": {
      "error": true,
      "name": "黄金",
      "updated": "2026-05-19T00:08:28.915015"
    },
    "GLD.US": {
      "error": true,
      "name": "黄金ETF",
      "updated": "2026-05-19T00:08:28.915388"
    },
    "XAGUSD": {
      "error": true,
      "name": "白银",
      "updated": "2026-05-19T00:08:31.175221"
    },
    "SLV.US": {
      "error": true,
      "name": "白银ETF",
      "updated": "2026-05-19T00:08:31.175533"
    },
    "HG=F": {
      "price": 6.333499908447266,
      "change_pct": 1.311681629149986,
      "prev_close": 6.251500129699707,
      "name": "铜",
      "updated": "2026-05-19T00:08:31.879343",
      "unit": "USD/吨",
      "icon": "🔶",
      "category": "metals"
    },
    "NICK.L": {
      "price": NaN,
      "change_pct": NaN,
      "prev_close": 16.155000686645508,
      "name": "镍",
      "updated": "2026-05-19T00:08:32.078583",
      "unit": "USD (ETC)",
      "icon": "⚙️",
      "category": "metals"
    },
    "CL=F": {
      "price": 102.44999694824219,
      "change_pct": -2.8173034265694286,
      "prev_close": 105.41999816894531,
      "name": "WTI原油",
      "updated": "2026-05-19T00:08:32.209735",
      "unit": "USD/桶",
      "icon": "🛢️",
      "category": "commodities"
    },
    "BTC-USD.CC": {
      "error": true,
      "name": "BTC",
      "updated": "2026-05-19T00:08:32.210092"
    },
    "ETH-USD.CC": {
      "error": true,
      "name": "ETH",
      "updated": "2026-05-19T00:08:32.210223"
    },
    "USDCNY.FOREX": {
      "error": true,
      "name": "USD/CNY",
      "updated": "2026-05-19T00:08:32.210345"
    },
    "USDJPY.FOREX": {
      "error": true,
      "name": "USD/JPY",
      "updated": "2026-05-19T00:08:32.210466"
    },
    "EURUSD.FOREX": {
      "error": true,
      "name": "USD/EUR",
      "updated": "2026-05-19T00:08:32.210595"
    },
    "US10Y.INDX": {
      "error": true,
      "name": "美国10年期国债收益率",
      "updated": "2026-05-19T00:08:32.210752"
    },
    "US30Y.INDX": {
      "error": true,
      "name": "美国30年期国债收益率",
      "updated": "2026-05-19T00:08:32.210899"
    }
  },
  "meta": {
    "total_assets": 14,
    "successful_fetches": 3,
    "failed_fetches": 11
  }
}