{
  "updated_at": "2026-02-06T13:59:18.717311",
  "assets": {
    "XAUUSD": {
      "price": 4925.685,
      "change_pct": 1.1917,
      "prev_close": 4867.6775,
      "name": "黄金",
      "updated": "2026-02-06T13:59:18.818485",
      "unit": "USD/oz",
      "icon": "🥇",
      "category": "metals"
    },
    "GLD.US": {
      "error": true,
      "name": "黄金ETF",
      "updated": "2026-02-06T13:59:19.342479"
    },
    "XAGUSD": {
      "price": 75.5935,
      "change_pct": -2.3365,
      "prev_close": 77.40205,
      "name": "白银",
      "updated": "2026-02-06T13:59:19.342548",
      "unit": "USD/oz",
      "icon": "🥈",
      "category": "metals"
    },
    "SLV.US": {
      "error": true,
      "name": "白银ETF",
      "updated": "2026-02-06T13:59:19.431581"
    },
    "HG=F": {
      "price": 5.815000057220459,
      "change_pct": 0.275914320278021,
      "prev_close": 5.798999786376953,
      "name": "铜",
      "updated": "2026-02-06T13:59:19.524228",
      "unit": "USD/吨",
      "icon": "🔶",
      "category": "metals"
    },
    "NICK.L": {
      "price": 14.975000381469727,
      "change_pct": -0.16666412353515625,
      "prev_close": 15.0,
      "name": "镍",
      "updated": "2026-02-06T13:59:19.612410",
      "unit": "USD (ETC)",
      "icon": "⚙️",
      "category": "metals"
    },
    "CL=F": {
      "price": 62.869998931884766,
      "change_pct": -0.6636150696271145,
      "prev_close": 63.290000915527344,
      "name": "WTI原油",
      "updated": "2026-02-06T13:59:19.697630",
      "unit": "USD/桶",
      "icon": "🛢️",
      "category": "commodities"
    },
    "BTC-USD.CC": {
      "error": true,
      "name": "BTC",
      "updated": "2026-02-06T13:59:19.697986"
    },
    "ETH-USD.CC": {
      "error": true,
      "name": "ETH",
      "updated": "2026-02-06T13:59:19.698081"
    },
    "USDCNY.FOREX": {
      "error": true,
      "name": "USD/CNY",
      "updated": "2026-02-06T13:59:19.698158"
    },
    "USDJPY.FOREX": {
      "error": true,
      "name": "USD/JPY",
      "updated": "2026-02-06T13:59:19.698243"
    },
    "EURUSD.FOREX": {
      "error": true,
      "name": "USD/EUR",
      "updated": "2026-02-06T13:59:19.698323"
    }
  },
  "meta": {
    "total_assets": 12,
    "successful_fetches": 5,
    "failed_fetches": 7
  }
}