{
  "updated_at": "2026-06-07T11:34:10.935195",
  "assets": {
    "XAUUSD": {
      "error": true,
      "name": "黄金",
      "updated": "2026-06-07T11:34:13.416464"
    },
    "GLD.US": {
      "error": true,
      "name": "黄金ETF",
      "updated": "2026-06-07T11:34:13.416879"
    },
    "XAGUSD": {
      "error": true,
      "name": "白银",
      "updated": "2026-06-07T11:34:15.534819"
    },
    "SLV.US": {
      "error": true,
      "name": "白银ETF",
      "updated": "2026-06-07T11:34:15.535148"
    },
    "HG=F": {
      "price": 6.2845001220703125,
      "change_pct": -3.4787287496767565,
      "prev_close": 6.511000156402588,
      "name": "铜",
      "updated": "2026-06-07T11:34:15.759782",
      "unit": "USD/吨",
      "icon": "🔶",
      "category": "metals"
    },
    "NICK.L": {
      "price": 16.15999984741211,
      "change_pct": -0.8893005522829928,
      "prev_close": 16.30500030517578,
      "name": "镍",
      "updated": "2026-06-07T11:34:15.831786",
      "unit": "USD (ETC)",
      "icon": "⚙️",
      "category": "metals"
    },
    "CL=F": {
      "price": 90.54000091552734,
      "change_pct": -2.687016310618692,
      "prev_close": 93.04000091552734,
      "name": "WTI原油",
      "updated": "2026-06-07T11:34:15.899878",
      "unit": "USD/桶",
      "icon": "🛢️",
      "category": "commodities"
    },
    "BTC-USD.CC": {
      "error": true,
      "name": "BTC",
      "updated": "2026-06-07T11:34:15.900210"
    },
    "ETH-USD.CC": {
      "error": true,
      "name": "ETH",
      "updated": "2026-06-07T11:34:15.900284"
    },
    "USDCNY.FOREX": {
      "error": true,
      "name": "USD/CNY",
      "updated": "2026-06-07T11:34:15.900387"
    },
    "USDJPY.FOREX": {
      "error": true,
      "name": "USD/JPY",
      "updated": "2026-06-07T11:34:15.900454"
    },
    "EURUSD.FOREX": {
      "error": true,
      "name": "USD/EUR",
      "updated": "2026-06-07T11:34:15.900514"
    },
    "US10Y.INDX": {
      "error": true,
      "name": "美国10年期国债收益率",
      "updated": "2026-06-07T11:34:15.900577"
    },
    "US30Y.INDX": {
      "error": true,
      "name": "美国30年期国债收益率",
      "updated": "2026-06-07T11:34:15.900642"
    },
    "HIBOR1M": {
      "error": true,
      "name": "香港1个月HIBOR",
      "updated": "2026-06-07T11:34:24.742791"
    }
  },
  "meta": {
    "total_assets": 15,
    "successful_fetches": 3,
    "failed_fetches": 12
  }
}