{
  "updated_at": "2026-02-23T07:58:29.842903",
  "assets": {
    "XAUUSD": {
      "price": 5138.3425,
      "change_pct": 0.62,
      "prev_close": 5106.68,
      "name": "黄金",
      "updated": "2026-02-23T07:58:30.069629",
      "unit": "USD/oz",
      "icon": "🥇",
      "category": "metals"
    },
    "GLD.US": {
      "error": true,
      "name": "黄金ETF",
      "updated": "2026-02-23T07:58:30.451450"
    },
    "XAGUSD": {
      "price": 85.943,
      "change_pct": 1.6025,
      "prev_close": 84.5875,
      "name": "白银",
      "updated": "2026-02-23T07:58:30.451530",
      "unit": "USD/oz",
      "icon": "🥈",
      "category": "metals"
    },
    "SLV.US": {
      "error": true,
      "name": "白银ETF",
      "updated": "2026-02-23T07:58:30.537259"
    },
    "HG=F": {
      "price": 5.820000171661377,
      "change_pct": -0.18864139677718259,
      "prev_close": 5.830999851226807,
      "name": "铜",
      "updated": "2026-02-23T07:58:30.626288",
      "unit": "USD/吨",
      "icon": "🔶",
      "category": "metals"
    },
    "NICK.L": {
      "price": 15.2524995803833,
      "change_pct": 0.5107043734718036,
      "prev_close": 15.175000190734863,
      "name": "镍",
      "updated": "2026-02-23T07:58:30.715433",
      "unit": "USD (ETC)",
      "icon": "⚙️",
      "category": "metals"
    },
    "CL=F": {
      "price": 65.56999969482422,
      "change_pct": -1.2351253236373332,
      "prev_close": 66.38999938964844,
      "name": "WTI原油",
      "updated": "2026-02-23T07:58:30.802193",
      "unit": "USD/桶",
      "icon": "🛢️",
      "category": "commodities"
    },
    "BTC-USD.CC": {
      "error": true,
      "name": "BTC",
      "updated": "2026-02-23T07:58:30.802510"
    },
    "ETH-USD.CC": {
      "error": true,
      "name": "ETH",
      "updated": "2026-02-23T07:58:30.802604"
    },
    "USDCNY.FOREX": {
      "error": true,
      "name": "USD/CNY",
      "updated": "2026-02-23T07:58:30.802690"
    },
    "USDJPY.FOREX": {
      "error": true,
      "name": "USD/JPY",
      "updated": "2026-02-23T07:58:30.802771"
    },
    "EURUSD.FOREX": {
      "error": true,
      "name": "USD/EUR",
      "updated": "2026-02-23T07:58:30.802852"
    }
  },
  "meta": {
    "total_assets": 12,
    "successful_fetches": 5,
    "failed_fetches": 7
  }
}